{
    "Status": true,
    "HttpStatus": 200,
    "Data": {
        "ShowAds": true,
        "Ads": [
			{
				"MonetizationId": 1,
				"MonetizerName": "Facebook Monetization",
				"AdAppKey": "8724785984213269",
				"BannerAdKey": "8724785984213269_8724791760879358",
				"InterstitialAdKey": "8724785984213269_8724793984212469",
				"RewardedAdKey": "8724785984213269_8724795387545662",
				"NativeAdKey": "8724785984213269_8724796434212224"
			},
            {
                "MonetizationId": 6,
                "MonetizerName": "ironSource",
                "AdAppKey": "16c3f24fd",
                "BannerAdKey": "",
                "InterstitialAdKey": "",
                "RewardedAdKey": "",
                "NativeAdKey": ""
            },
			{
				"MonetizationId": 5,
				"MonetizerName": "UnityAds",
				"AdAppKey": "4960426",
				"BannerAdKey": "Banner_Android",
				"InterstitialAdKey": "Interstitial_Android",
				"RewardedAdKey": "Rewarded_Android",
				"NativeAdKey": ""
			}
        ]
    },
    "Message": "Data loaded."
}